telegramlib/__init__.py
telegramlib/commands.py
telegramlib/config.py
telegramlib/core.py
telegramlib/data.py
telegramlib/firma.py
telegramlib/jobs.py
telegramlib/telegram_exceptions.py
telegramlib/telegram_warnings.py
telegramlib/text_to_speech.py
telegramlib/translator.py
telegramlib/utils.py
telegramlib-0.1.3.dist-info/LICENSE
telegramlib-0.1.3.dist-info/METADATA
telegramlib-0.1.3.dist-info/WHEEL
telegramlib-0.1.3.dist-info/top_level.txt
telegramlib-0.1.3.dist-info/RECORD
